{"efVersion":"0.13.6","efModuleName":["Node","HTTP"],"efExports":[{"TypeRef":[{"start":[3,1],"name":"bower_components/purescript-node-http/src/Node/HTTP.purs","end":[104,32]},"Server",[]]},{"TypeRef":[{"start":[3,1],"name":"bower_components/purescript-node-http/src/Node/HTTP.purs","end":[104,32]},"Request",[]]},{"TypeRef":[{"start":[3,1],"name":"bower_components/purescript-node-http/src/Node/HTTP.purs","end":[104,32]},"Response",[]]},{"ValueRef":[{"start":[3,1],"name":"bower_components/purescript-node-http/src/Node/HTTP.purs","end":[104,32]},{"Ident":"createServer"}]},{"ValueRef":[{"start":[3,1],"name":"bower_components/purescript-node-http/src/Node/HTTP.purs","end":[104,32]},{"Ident":"listen"}]},{"ValueRef":[{"start":[3,1],"name":"bower_components/purescript-node-http/src/Node/HTTP.purs","end":[104,32]},{"Ident":"close"}]},{"TypeRef":[{"start":[3,1],"name":"bower_components/purescript-node-http/src/Node/HTTP.purs","end":[104,32]},"ListenOptions",[]]},{"ValueRef":[{"start":[3,1],"name":"bower_components/purescript-node-http/src/Node/HTTP.purs","end":[104,32]},{"Ident":"listenSocket"}]},{"ValueRef":[{"start":[3,1],"name":"bower_components/purescript-node-http/src/Node/HTTP.purs","end":[104,32]},{"Ident":"httpVersion"}]},{"ValueRef":[{"start":[3,1],"name":"bower_components/purescript-node-http/src/Node/HTTP.purs","end":[104,32]},{"Ident":"requestHeaders"}]},{"ValueRef":[{"start":[3,1],"name":"bower_components/purescript-node-http/src/Node/HTTP.purs","end":[104,32]},{"Ident":"requestMethod"}]},{"ValueRef":[{"start":[3,1],"name":"bower_components/purescript-node-http/src/Node/HTTP.purs","end":[104,32]},{"Ident":"requestURL"}]},{"ValueRef":[{"start":[3,1],"name":"bower_components/purescript-node-http/src/Node/HTTP.purs","end":[104,32]},{"Ident":"requestAsStream"}]},{"ValueRef":[{"start":[3,1],"name":"bower_components/purescript-node-http/src/Node/HTTP.purs","end":[104,32]},{"Ident":"setHeader"}]},{"ValueRef":[{"start":[3,1],"name":"bower_components/purescript-node-http/src/Node/HTTP.purs","end":[104,32]},{"Ident":"setHeaders"}]},{"ValueRef":[{"start":[3,1],"name":"bower_components/purescript-node-http/src/Node/HTTP.purs","end":[104,32]},{"Ident":"setStatusCode"}]},{"ValueRef":[{"start":[3,1],"name":"bower_components/purescript-node-http/src/Node/HTTP.purs","end":[104,32]},{"Ident":"setStatusMessage"}]},{"ValueRef":[{"start":[3,1],"name":"bower_components/purescript-node-http/src/Node/HTTP.purs","end":[104,32]},{"Ident":"responseAsStream"}]}],"efImports":[{"eiModule":["Prim"],"eiImportType":{"Implicit":[]},"eiImportedAs":["Prim"]},{"eiModule":["Prim"],"eiImportType":{"Implicit":[]},"eiImportedAs":null},{"eiModule":["Prelude"],"eiImportType":{"Implicit":[]},"eiImportedAs":null},{"eiModule":["Data","Maybe"],"eiImportType":{"Explicit":[{"TypeRef":[{"start":[29,20],"name":"bower_components/purescript-node-http/src/Node/HTTP.purs","end":[29,25]},"Maybe",[]]}]},"eiImportedAs":null},{"eiModule":["Data","Nullable"],"eiImportType":{"Explicit":[{"TypeRef":[{"start":[30,23],"name":"bower_components/purescript-node-http/src/Node/HTTP.purs","end":[30,31]},"Nullable",[]]},{"ValueRef":[{"start":[30,33],"name":"bower_components/purescript-node-http/src/Node/HTTP.purs","end":[30,43]},{"Ident":"toNullable"}]}]},"eiImportedAs":null},{"eiModule":["Effect"],"eiImportType":{"Explicit":[{"TypeRef":[{"start":[31,16],"name":"bower_components/purescript-node-http/src/Node/HTTP.purs","end":[31,22]},"Effect",[]]}]},"eiImportedAs":null},{"eiModule":["Foreign","Object"],"eiImportType":{"Explicit":[{"TypeRef":[{"start":[32,24],"name":"bower_components/purescript-node-http/src/Node/HTTP.purs","end":[32,30]},"Object",[]]}]},"eiImportedAs":null},{"eiModule":["Node","Stream"],"eiImportType":{"Explicit":[{"TypeRef":[{"start":[33,21],"name":"bower_components/purescript-node-http/src/Node/HTTP.purs","end":[33,29]},"Writable",[]]},{"TypeRef":[{"start":[33,31],"name":"bower_components/purescript-node-http/src/Node/HTTP.purs","end":[33,39]},"Readable",[]]}]},"eiImportedAs":null},{"eiModule":["Unsafe","Coerce"],"eiImportType":{"Explicit":[{"ValueRef":[{"start":[34,23],"name":"bower_components/purescript-node-http/src/Node/HTTP.purs","end":[34,35]},{"Ident":"unsafeCoerce"}]}]},"eiImportedAs":null}],"efFixities":[],"efTypeFixities":[],"efDeclarations":[{"EDType":{"edTypeName":"Server","edTypeKind":{"annotation":[{"start":[37,31],"name":"bower_components/purescript-node-http/src/Node/HTTP.purs","end":[37,35]},[]],"tag":"NamedKind","contents":[["Prim"],"Type"]},"edTypeDeclarationKind":"ExternData"}},{"EDType":{"edTypeName":"Request","edTypeKind":{"annotation":[{"start":[40,32],"name":"bower_components/purescript-node-http/src/Node/HTTP.purs","end":[40,36]},[]],"tag":"NamedKind","contents":[["Prim"],"Type"]},"edTypeDeclarationKind":"ExternData"}},{"EDType":{"edTypeName":"Response","edTypeKind":{"annotation":[{"start":[43,33],"name":"bower_components/purescript-node-http/src/Node/HTTP.purs","end":[43,37]},[]],"tag":"NamedKind","contents":[["Prim"],"Type"]},"edTypeDeclarationKind":"ExternData"}},{"EDValue":{"edValueName":{"Ident":"createServer"},"edValueType":{"annotation":[{"start":[46,32],"name":"bower_components/purescript-node-http/src/Node/HTTP.purs","end":[46,85]},[]],"tag":"TypeApp","contents":[{"annotation":[{"start":[46,32],"name":"bower_components/purescript-node-http/src/Node/HTTP.purs","end":[46,85]},[]],"tag":"TypeApp","contents":[{"annotation":[{"start":[46,69],"name":"bower_components/purescript-node-http/src/Node/HTTP.purs","end":[46,71]},[]],"tag":"TypeConstructor","contents":[["Prim"],"Function"]},{"annotation":[{"start":[46,33],"name":"bower_components/purescript-node-http/src/Node/HTTP.purs","end":[46,67]},[]],"tag":"TypeApp","contents":[{"annotation":[{"start":[46,33],"name":"bower_components/purescript-node-http/src/Node/HTTP.purs","end":[46,67]},[]],"tag":"TypeApp","contents":[{"annotation":[{"start":[46,41],"name":"bower_components/purescript-node-http/src/Node/HTTP.purs","end":[46,43]},[]],"tag":"TypeConstructor","contents":[["Prim"],"Function"]},{"annotation":[{"start":[46,33],"name":"bower_components/purescript-node-http/src/Node/HTTP.purs","end":[46,40]},[]],"tag":"TypeConstructor","contents":[["Node","HTTP"],"Request"]}]},{"annotation":[{"start":[46,44],"name":"bower_components/purescript-node-http/src/Node/HTTP.purs","end":[46,67]},[]],"tag":"TypeApp","contents":[{"annotation":[{"start":[46,44],"name":"bower_components/purescript-node-http/src/Node/HTTP.purs","end":[46,67]},[]],"tag":"TypeApp","contents":[{"annotation":[{"start":[46,53],"name":"bower_components/purescript-node-http/src/Node/HTTP.purs","end":[46,55]},[]],"tag":"TypeConstructor","contents":[["Prim"],"Function"]},{"annotation":[{"start":[46,44],"name":"bower_components/purescript-node-http/src/Node/HTTP.purs","end":[46,52]},[]],"tag":"TypeConstructor","contents":[["Node","HTTP"],"Response"]}]},{"annotation":[{"start":[46,56],"name":"bower_components/purescript-node-http/src/Node/HTTP.purs","end":[46,67]},[]],"tag":"TypeApp","contents":[{"annotation":[{"start":[46,56],"name":"bower_components/purescript-node-http/src/Node/HTTP.purs","end":[46,62]},[]],"tag":"TypeConstructor","contents":[["Effect"],"Effect"]},{"annotation":[{"start":[46,63],"name":"bower_components/purescript-node-http/src/Node/HTTP.purs","end":[46,67]},[]],"tag":"TypeConstructor","contents":[["Data","Unit"],"Unit"]}]}]}]}]},{"annotation":[{"start":[46,72],"name":"bower_components/purescript-node-http/src/Node/HTTP.purs","end":[46,85]},[]],"tag":"TypeApp","contents":[{"annotation":[{"start":[46,72],"name":"bower_components/purescript-node-http/src/Node/HTTP.purs","end":[46,78]},[]],"tag":"TypeConstructor","contents":[["Effect"],"Effect"]},{"annotation":[{"start":[46,79],"name":"bower_components/purescript-node-http/src/Node/HTTP.purs","end":[46,85]},[]],"tag":"TypeConstructor","contents":[["Node","HTTP"],"Server"]}]}]}}},{"EDValue":{"edValueName":{"Ident":"listen"},"edValueType":{"annotation":[{"start":[53,11],"name":"bower_components/purescript-node-http/src/Node/HTTP.purs","end":[53,64]},[]],"tag":"TypeApp","contents":[{"annotation":[{"start":[53,11],"name":"bower_components/purescript-node-http/src/Node/HTTP.purs","end":[53,64]},[]],"tag":"TypeApp","contents":[{"annotation":[{"start":[53,18],"name":"bower_components/purescript-node-http/src/Node/HTTP.purs","end":[53,20]},[]],"tag":"TypeConstructor","contents":[["Prim"],"Function"]},{"annotation":[{"start":[53,11],"name":"bower_components/purescript-node-http/src/Node/HTTP.purs","end":[53,17]},[]],"tag":"TypeConstructor","contents":[["Node","HTTP"],"Server"]}]},{"annotation":[{"start":[53,21],"name":"bower_components/purescript-node-http/src/Node/HTTP.purs","end":[53,64]},[]],"tag":"TypeApp","contents":[{"annotation":[{"start":[53,21],"name":"bower_components/purescript-node-http/src/Node/HTTP.purs","end":[53,64]},[]],"tag":"TypeApp","contents":[{"annotation":[{"start":[53,35],"name":"bower_components/purescript-node-http/src/Node/HTTP.purs","end":[53,37]},[]],"tag":"TypeConstructor","contents":[["Prim"],"Function"]},{"annotation":[{"start":[62,3],"name":"bower_components/purescript-node-http/src/Node/HTTP.purs","end":[65,4]},[]],"tag":"TypeApp","contents":[{"annotation":[{"start":[62,3],"name":"bower_components/purescript-node-http/src/Node/HTTP.purs","end":[62,4]},[]],"tag":"TypeConstructor","contents":[["Prim"],"Record"]},{"annotation":[{"start":[62,5],"name":"bower_components/purescript-node-http/src/Node/HTTP.purs","end":[62,23]},[]],"tag":"RCons","contents":["hostname",{"annotation":[{"start":[62,17],"name":"bower_components/purescript-node-http/src/Node/HTTP.purs","end":[62,23]},[]],"tag":"TypeConstructor","contents":[["Prim"],"String"]},{"annotation":[{"start":[63,5],"name":"bower_components/purescript-node-http/src/Node/HTTP.purs","end":[63,16]},[]],"tag":"RCons","contents":["port",{"annotation":[{"start":[63,13],"name":"bower_components/purescript-node-http/src/Node/HTTP.purs","end":[63,16]},[]],"tag":"TypeConstructor","contents":[["Prim"],"Int"]},{"annotation":[{"start":[64,5],"name":"bower_components/purescript-node-http/src/Node/HTTP.purs","end":[64,25]},[]],"tag":"RCons","contents":["backlog",{"annotation":[{"start":[64,16],"name":"bower_components/purescript-node-http/src/Node/HTTP.purs","end":[64,25]},[]],"tag":"TypeApp","contents":[{"annotation":[{"start":[64,16],"name":"bower_components/purescript-node-http/src/Node/HTTP.purs","end":[64,21]},[]],"tag":"TypeConstructor","contents":[["Data","Maybe"],"Maybe"]},{"annotation":[{"start":[64,22],"name":"bower_components/purescript-node-http/src/Node/HTTP.purs","end":[64,25]},[]],"tag":"TypeConstructor","contents":[["Prim"],"Int"]}]},{"annotation":[{"start":[65,3],"name":"bower_components/purescript-node-http/src/Node/HTTP.purs","end":[65,4]},[]],"tag":"REmpty"}]}]}]}]}]},{"annotation":[{"start":[53,38],"name":"bower_components/purescript-node-http/src/Node/HTTP.purs","end":[53,64]},[]],"tag":"TypeApp","contents":[{"annotation":[{"start":[53,38],"name":"bower_components/purescript-node-http/src/Node/HTTP.purs","end":[53,64]},[]],"tag":"TypeApp","contents":[{"annotation":[{"start":[53,50],"name":"bower_components/purescript-node-http/src/Node/HTTP.purs","end":[53,52]},[]],"tag":"TypeConstructor","contents":[["Prim"],"Function"]},{"annotation":[{"start":[53,38],"name":"bower_components/purescript-node-http/src/Node/HTTP.purs","end":[53,49]},[]],"tag":"TypeApp","contents":[{"annotation":[{"start":[53,38],"name":"bower_components/purescript-node-http/src/Node/HTTP.purs","end":[53,44]},[]],"tag":"TypeConstructor","contents":[["Effect"],"Effect"]},{"annotation":[{"start":[53,45],"name":"bower_components/purescript-node-http/src/Node/HTTP.purs","end":[53,49]},[]],"tag":"TypeConstructor","contents":[["Data","Unit"],"Unit"]}]}]},{"annotation":[{"start":[53,53],"name":"bower_components/purescript-node-http/src/Node/HTTP.purs","end":[53,64]},[]],"tag":"TypeApp","contents":[{"annotation":[{"start":[53,53],"name":"bower_components/purescript-node-http/src/Node/HTTP.purs","end":[53,59]},[]],"tag":"TypeConstructor","contents":[["Effect"],"Effect"]},{"annotation":[{"start":[53,60],"name":"bower_components/purescript-node-http/src/Node/HTTP.purs","end":[53,64]},[]],"tag":"TypeConstructor","contents":[["Data","Unit"],"Unit"]}]}]}]}]}}},{"EDValue":{"edValueName":{"Ident":"close"},"edValueType":{"annotation":[{"start":[57,10],"name":"bower_components/purescript-node-http/src/Node/HTTP.purs","end":[57,46]},[]],"tag":"TypeApp","contents":[{"annotation":[{"start":[57,10],"name":"bower_components/purescript-node-http/src/Node/HTTP.purs","end":[57,46]},[]],"tag":"TypeApp","contents":[{"annotation":[{"start":[57,17],"name":"bower_components/purescript-node-http/src/Node/HTTP.purs","end":[57,19]},[]],"tag":"TypeConstructor","contents":[["Prim"],"Function"]},{"annotation":[{"start":[57,10],"name":"bower_components/purescript-node-http/src/Node/HTTP.purs","end":[57,16]},[]],"tag":"TypeConstructor","contents":[["Node","HTTP"],"Server"]}]},{"annotation":[{"start":[57,20],"name":"bower_components/purescript-node-http/src/Node/HTTP.purs","end":[57,46]},[]],"tag":"TypeApp","contents":[{"annotation":[{"start":[57,20],"name":"bower_components/purescript-node-http/src/Node/HTTP.purs","end":[57,46]},[]],"tag":"TypeApp","contents":[{"annotation":[{"start":[57,32],"name":"bower_components/purescript-node-http/src/Node/HTTP.purs","end":[57,34]},[]],"tag":"TypeConstructor","contents":[["Prim"],"Function"]},{"annotation":[{"start":[57,20],"name":"bower_components/purescript-node-http/src/Node/HTTP.purs","end":[57,31]},[]],"tag":"TypeApp","contents":[{"annotation":[{"start":[57,20],"name":"bower_components/purescript-node-http/src/Node/HTTP.purs","end":[57,26]},[]],"tag":"TypeConstructor","contents":[["Effect"],"Effect"]},{"annotation":[{"start":[57,27],"name":"bower_components/purescript-node-http/src/Node/HTTP.purs","end":[57,31]},[]],"tag":"TypeConstructor","contents":[["Data","Unit"],"Unit"]}]}]},{"annotation":[{"start":[57,35],"name":"bower_components/purescript-node-http/src/Node/HTTP.purs","end":[57,46]},[]],"tag":"TypeApp","contents":[{"annotation":[{"start":[57,35],"name":"bower_components/purescript-node-http/src/Node/HTTP.purs","end":[57,41]},[]],"tag":"TypeConstructor","contents":[["Effect"],"Effect"]},{"annotation":[{"start":[57,42],"name":"bower_components/purescript-node-http/src/Node/HTTP.purs","end":[57,46]},[]],"tag":"TypeConstructor","contents":[["Data","Unit"],"Unit"]}]}]}]}}},{"EDType":{"edTypeName":"ListenOptions","edTypeKind":{"annotation":[{"start":[62,3],"name":"bower_components/purescript-node-http/src/Node/HTTP.purs","end":[62,4]},[]],"tag":"NamedKind","contents":[["Prim"],"Type"]},"edTypeDeclarationKind":"TypeSynonym"}},{"EDTypeSynonym":{"edTypeSynonymName":"ListenOptions","edTypeSynonymArguments":[],"edTypeSynonymType":{"annotation":[{"start":[62,3],"name":"bower_components/purescript-node-http/src/Node/HTTP.purs","end":[65,4]},[]],"tag":"TypeApp","contents":[{"annotation":[{"start":[62,3],"name":"bower_components/purescript-node-http/src/Node/HTTP.purs","end":[62,4]},[]],"tag":"TypeConstructor","contents":[["Prim"],"Record"]},{"annotation":[{"start":[62,5],"name":"bower_components/purescript-node-http/src/Node/HTTP.purs","end":[62,23]},[]],"tag":"RCons","contents":["hostname",{"annotation":[{"start":[62,17],"name":"bower_components/purescript-node-http/src/Node/HTTP.purs","end":[62,23]},[]],"tag":"TypeConstructor","contents":[["Prim"],"String"]},{"annotation":[{"start":[63,5],"name":"bower_components/purescript-node-http/src/Node/HTTP.purs","end":[63,16]},[]],"tag":"RCons","contents":["port",{"annotation":[{"start":[63,13],"name":"bower_components/purescript-node-http/src/Node/HTTP.purs","end":[63,16]},[]],"tag":"TypeConstructor","contents":[["Prim"],"Int"]},{"annotation":[{"start":[64,5],"name":"bower_components/purescript-node-http/src/Node/HTTP.purs","end":[64,25]},[]],"tag":"RCons","contents":["backlog",{"annotation":[{"start":[64,16],"name":"bower_components/purescript-node-http/src/Node/HTTP.purs","end":[64,25]},[]],"tag":"TypeApp","contents":[{"annotation":[{"start":[64,16],"name":"bower_components/purescript-node-http/src/Node/HTTP.purs","end":[64,21]},[]],"tag":"TypeConstructor","contents":[["Data","Maybe"],"Maybe"]},{"annotation":[{"start":[64,22],"name":"bower_components/purescript-node-http/src/Node/HTTP.purs","end":[64,25]},[]],"tag":"TypeConstructor","contents":[["Prim"],"Int"]}]},{"annotation":[{"start":[65,3],"name":"bower_components/purescript-node-http/src/Node/HTTP.purs","end":[65,4]},[]],"tag":"REmpty"}]}]}]}]}}},{"EDValue":{"edValueName":{"Ident":"listenSocket"},"edValueType":{"annotation":[{"start":[68,32],"name":"bower_components/purescript-node-http/src/Node/HTTP.purs","end":[68,78]},[]],"tag":"TypeApp","contents":[{"annotation":[{"start":[68,32],"name":"bower_components/purescript-node-http/src/Node/HTTP.purs","end":[68,78]},[]],"tag":"TypeApp","contents":[{"annotation":[{"start":[68,39],"name":"bower_components/purescript-node-http/src/Node/HTTP.purs","end":[68,41]},[]],"tag":"TypeConstructor","contents":[["Prim"],"Function"]},{"annotation":[{"start":[68,32],"name":"bower_components/purescript-node-http/src/Node/HTTP.purs","end":[68,38]},[]],"tag":"TypeConstructor","contents":[["Node","HTTP"],"Server"]}]},{"annotation":[{"start":[68,42],"name":"bower_components/purescript-node-http/src/Node/HTTP.purs","end":[68,78]},[]],"tag":"TypeApp","contents":[{"annotation":[{"start":[68,42],"name":"bower_components/purescript-node-http/src/Node/HTTP.purs","end":[68,78]},[]],"tag":"TypeApp","contents":[{"annotation":[{"start":[68,49],"name":"bower_components/purescript-node-http/src/Node/HTTP.purs","end":[68,51]},[]],"tag":"TypeConstructor","contents":[["Prim"],"Function"]},{"annotation":[{"start":[68,42],"name":"bower_components/purescript-node-http/src/Node/HTTP.purs","end":[68,48]},[]],"tag":"TypeConstructor","contents":[["Prim"],"String"]}]},{"annotation":[{"start":[68,52],"name":"bower_components/purescript-node-http/src/Node/HTTP.purs","end":[68,78]},[]],"tag":"TypeApp","contents":[{"annotation":[{"start":[68,52],"name":"bower_components/purescript-node-http/src/Node/HTTP.purs","end":[68,78]},[]],"tag":"TypeApp","contents":[{"annotation":[{"start":[68,64],"name":"bower_components/purescript-node-http/src/Node/HTTP.purs","end":[68,66]},[]],"tag":"TypeConstructor","contents":[["Prim"],"Function"]},{"annotation":[{"start":[68,52],"name":"bower_components/purescript-node-http/src/Node/HTTP.purs","end":[68,63]},[]],"tag":"TypeApp","contents":[{"annotation":[{"start":[68,52],"name":"bower_components/purescript-node-http/src/Node/HTTP.purs","end":[68,58]},[]],"tag":"TypeConstructor","contents":[["Effect"],"Effect"]},{"annotation":[{"start":[68,59],"name":"bower_components/purescript-node-http/src/Node/HTTP.purs","end":[68,63]},[]],"tag":"TypeConstructor","contents":[["Data","Unit"],"Unit"]}]}]},{"annotation":[{"start":[68,67],"name":"bower_components/purescript-node-http/src/Node/HTTP.purs","end":[68,78]},[]],"tag":"TypeApp","contents":[{"annotation":[{"start":[68,67],"name":"bower_components/purescript-node-http/src/Node/HTTP.purs","end":[68,73]},[]],"tag":"TypeConstructor","contents":[["Effect"],"Effect"]},{"annotation":[{"start":[68,74],"name":"bower_components/purescript-node-http/src/Node/HTTP.purs","end":[68,78]},[]],"tag":"TypeConstructor","contents":[["Data","Unit"],"Unit"]}]}]}]}]}}},{"EDValue":{"edValueName":{"Ident":"httpVersion"},"edValueType":{"annotation":[{"start":[71,16],"name":"bower_components/purescript-node-http/src/Node/HTTP.purs","end":[71,33]},[]],"tag":"TypeApp","contents":[{"annotation":[{"start":[71,16],"name":"bower_components/purescript-node-http/src/Node/HTTP.purs","end":[71,33]},[]],"tag":"TypeApp","contents":[{"annotation":[{"start":[71,24],"name":"bower_components/purescript-node-http/src/Node/HTTP.purs","end":[71,26]},[]],"tag":"TypeConstructor","contents":[["Prim"],"Function"]},{"annotation":[{"start":[71,16],"name":"bower_components/purescript-node-http/src/Node/HTTP.purs","end":[71,23]},[]],"tag":"TypeConstructor","contents":[["Node","HTTP"],"Request"]}]},{"annotation":[{"start":[71,27],"name":"bower_components/purescript-node-http/src/Node/HTTP.purs","end":[71,33]},[]],"tag":"TypeConstructor","contents":[["Prim"],"String"]}]}}},{"EDValue":{"edValueName":{"Ident":"requestHeaders"},"edValueType":{"annotation":[{"start":[75,19],"name":"bower_components/purescript-node-http/src/Node/HTTP.purs","end":[75,43]},[]],"tag":"TypeApp","contents":[{"annotation":[{"start":[75,19],"name":"bower_components/purescript-node-http/src/Node/HTTP.purs","end":[75,43]},[]],"tag":"TypeApp","contents":[{"annotation":[{"start":[75,27],"name":"bower_components/purescript-node-http/src/Node/HTTP.purs","end":[75,29]},[]],"tag":"TypeConstructor","contents":[["Prim"],"Function"]},{"annotation":[{"start":[75,19],"name":"bower_components/purescript-node-http/src/Node/HTTP.purs","end":[75,26]},[]],"tag":"TypeConstructor","contents":[["Node","HTTP"],"Request"]}]},{"annotation":[{"start":[75,30],"name":"bower_components/purescript-node-http/src/Node/HTTP.purs","end":[75,43]},[]],"tag":"TypeApp","contents":[{"annotation":[{"start":[75,30],"name":"bower_components/purescript-node-http/src/Node/HTTP.purs","end":[75,36]},[]],"tag":"TypeConstructor","contents":[["Foreign","Object"],"Object"]},{"annotation":[{"start":[75,37],"name":"bower_components/purescript-node-http/src/Node/HTTP.purs","end":[75,43]},[]],"tag":"TypeConstructor","contents":[["Prim"],"String"]}]}]}}},{"EDValue":{"edValueName":{"Ident":"requestMethod"},"edValueType":{"annotation":[{"start":[79,18],"name":"bower_components/purescript-node-http/src/Node/HTTP.purs","end":[79,35]},[]],"tag":"TypeApp","contents":[{"annotation":[{"start":[79,18],"name":"bower_components/purescript-node-http/src/Node/HTTP.purs","end":[79,35]},[]],"tag":"TypeApp","contents":[{"annotation":[{"start":[79,26],"name":"bower_components/purescript-node-http/src/Node/HTTP.purs","end":[79,28]},[]],"tag":"TypeConstructor","contents":[["Prim"],"Function"]},{"annotation":[{"start":[79,18],"name":"bower_components/purescript-node-http/src/Node/HTTP.purs","end":[79,25]},[]],"tag":"TypeConstructor","contents":[["Node","HTTP"],"Request"]}]},{"annotation":[{"start":[79,29],"name":"bower_components/purescript-node-http/src/Node/HTTP.purs","end":[79,35]},[]],"tag":"TypeConstructor","contents":[["Prim"],"String"]}]}}},{"EDValue":{"edValueName":{"Ident":"requestURL"},"edValueType":{"annotation":[{"start":[83,15],"name":"bower_components/purescript-node-http/src/Node/HTTP.purs","end":[83,32]},[]],"tag":"TypeApp","contents":[{"annotation":[{"start":[83,15],"name":"bower_components/purescript-node-http/src/Node/HTTP.purs","end":[83,32]},[]],"tag":"TypeApp","contents":[{"annotation":[{"start":[83,23],"name":"bower_components/purescript-node-http/src/Node/HTTP.purs","end":[83,25]},[]],"tag":"TypeConstructor","contents":[["Prim"],"Function"]},{"annotation":[{"start":[83,15],"name":"bower_components/purescript-node-http/src/Node/HTTP.purs","end":[83,22]},[]],"tag":"TypeConstructor","contents":[["Node","HTTP"],"Request"]}]},{"annotation":[{"start":[83,26],"name":"bower_components/purescript-node-http/src/Node/HTTP.purs","end":[83,32]},[]],"tag":"TypeConstructor","contents":[["Prim"],"String"]}]}}},{"EDValue":{"edValueName":{"Ident":"requestAsStream"},"edValueType":{"annotation":[{"start":[87,20],"name":"bower_components/purescript-node-http/src/Node/HTTP.purs","end":[87,42]},[]],"tag":"TypeApp","contents":[{"annotation":[{"start":[87,20],"name":"bower_components/purescript-node-http/src/Node/HTTP.purs","end":[87,42]},[]],"tag":"TypeApp","contents":[{"annotation":[{"start":[87,28],"name":"bower_components/purescript-node-http/src/Node/HTTP.purs","end":[87,30]},[]],"tag":"TypeConstructor","contents":[["Prim"],"Function"]},{"annotation":[{"start":[87,20],"name":"bower_components/purescript-node-http/src/Node/HTTP.purs","end":[87,27]},[]],"tag":"TypeConstructor","contents":[["Node","HTTP"],"Request"]}]},{"annotation":[{"start":[59,19],"name":"bower_components/purescript-node-streams/src/Node/Stream.purs","end":[59,39]},[]],"tag":"TypeApp","contents":[{"annotation":[{"start":[59,19],"name":"bower_components/purescript-node-streams/src/Node/Stream.purs","end":[59,25]},[]],"tag":"TypeConstructor","contents":[["Node","Stream"],"Stream"]},{"annotation":[{"start":[59,27],"name":"bower_components/purescript-node-streams/src/Node/Stream.purs","end":[59,39]},[]],"tag":"RCons","contents":["read",{"annotation":[{"start":[59,35],"name":"bower_components/purescript-node-streams/src/Node/Stream.purs","end":[59,39]},[]],"tag":"TypeConstructor","contents":[["Node","Stream"],"Read"]},{"annotation":[{"start":[87,41],"name":"bower_components/purescript-node-http/src/Node/HTTP.purs","end":[87,42]},[]],"tag":"REmpty"}]}]}]}}},{"EDValue":{"edValueName":{"Ident":"setHeader"},"edValueType":{"annotation":[{"start":[91,29],"name":"bower_components/purescript-node-http/src/Node/HTTP.purs","end":[91,72]},[]],"tag":"TypeApp","contents":[{"annotation":[{"start":[91,29],"name":"bower_components/purescript-node-http/src/Node/HTTP.purs","end":[91,72]},[]],"tag":"TypeApp","contents":[{"annotation":[{"start":[91,38],"name":"bower_components/purescript-node-http/src/Node/HTTP.purs","end":[91,40]},[]],"tag":"TypeConstructor","contents":[["Prim"],"Function"]},{"annotation":[{"start":[91,29],"name":"bower_components/purescript-node-http/src/Node/HTTP.purs","end":[91,37]},[]],"tag":"TypeConstructor","contents":[["Node","HTTP"],"Response"]}]},{"annotation":[{"start":[91,41],"name":"bower_components/purescript-node-http/src/Node/HTTP.purs","end":[91,72]},[]],"tag":"TypeApp","contents":[{"annotation":[{"start":[91,41],"name":"bower_components/purescript-node-http/src/Node/HTTP.purs","end":[91,72]},[]],"tag":"TypeApp","contents":[{"annotation":[{"start":[91,48],"name":"bower_components/purescript-node-http/src/Node/HTTP.purs","end":[91,50]},[]],"tag":"TypeConstructor","contents":[["Prim"],"Function"]},{"annotation":[{"start":[91,41],"name":"bower_components/purescript-node-http/src/Node/HTTP.purs","end":[91,47]},[]],"tag":"TypeConstructor","contents":[["Prim"],"String"]}]},{"annotation":[{"start":[91,51],"name":"bower_components/purescript-node-http/src/Node/HTTP.purs","end":[91,72]},[]],"tag":"TypeApp","contents":[{"annotation":[{"start":[91,51],"name":"bower_components/purescript-node-http/src/Node/HTTP.purs","end":[91,72]},[]],"tag":"TypeApp","contents":[{"annotation":[{"start":[91,58],"name":"bower_components/purescript-node-http/src/Node/HTTP.purs","end":[91,60]},[]],"tag":"TypeConstructor","contents":[["Prim"],"Function"]},{"annotation":[{"start":[91,51],"name":"bower_components/purescript-node-http/src/Node/HTTP.purs","end":[91,57]},[]],"tag":"TypeConstructor","contents":[["Prim"],"String"]}]},{"annotation":[{"start":[91,61],"name":"bower_components/purescript-node-http/src/Node/HTTP.purs","end":[91,72]},[]],"tag":"TypeApp","contents":[{"annotation":[{"start":[91,61],"name":"bower_components/purescript-node-http/src/Node/HTTP.purs","end":[91,67]},[]],"tag":"TypeConstructor","contents":[["Effect"],"Effect"]},{"annotation":[{"start":[91,68],"name":"bower_components/purescript-node-http/src/Node/HTTP.purs","end":[91,72]},[]],"tag":"TypeConstructor","contents":[["Data","Unit"],"Unit"]}]}]}]}]}}},{"EDValue":{"edValueName":{"Ident":"setHeaders"},"edValueType":{"annotation":[{"start":[94,30],"name":"bower_components/purescript-node-http/src/Node/HTTP.purs","end":[94,79]},[]],"tag":"TypeApp","contents":[{"annotation":[{"start":[94,30],"name":"bower_components/purescript-node-http/src/Node/HTTP.purs","end":[94,79]},[]],"tag":"TypeApp","contents":[{"annotation":[{"start":[94,39],"name":"bower_components/purescript-node-http/src/Node/HTTP.purs","end":[94,41]},[]],"tag":"TypeConstructor","contents":[["Prim"],"Function"]},{"annotation":[{"start":[94,30],"name":"bower_components/purescript-node-http/src/Node/HTTP.purs","end":[94,38]},[]],"tag":"TypeConstructor","contents":[["Node","HTTP"],"Response"]}]},{"annotation":[{"start":[94,42],"name":"bower_components/purescript-node-http/src/Node/HTTP.purs","end":[94,79]},[]],"tag":"TypeApp","contents":[{"annotation":[{"start":[94,42],"name":"bower_components/purescript-node-http/src/Node/HTTP.purs","end":[94,79]},[]],"tag":"TypeApp","contents":[{"annotation":[{"start":[94,49],"name":"bower_components/purescript-node-http/src/Node/HTTP.purs","end":[94,51]},[]],"tag":"TypeConstructor","contents":[["Prim"],"Function"]},{"annotation":[{"start":[94,42],"name":"bower_components/purescript-node-http/src/Node/HTTP.purs","end":[94,48]},[]],"tag":"TypeConstructor","contents":[["Prim"],"String"]}]},{"annotation":[{"start":[94,52],"name":"bower_components/purescript-node-http/src/Node/HTTP.purs","end":[94,79]},[]],"tag":"TypeApp","contents":[{"annotation":[{"start":[94,52],"name":"bower_components/purescript-node-http/src/Node/HTTP.purs","end":[94,79]},[]],"tag":"TypeApp","contents":[{"annotation":[{"start":[94,65],"name":"bower_components/purescript-node-http/src/Node/HTTP.purs","end":[94,67]},[]],"tag":"TypeConstructor","contents":[["Prim"],"Function"]},{"annotation":[{"start":[94,52],"name":"bower_components/purescript-node-http/src/Node/HTTP.purs","end":[94,64]},[]],"tag":"TypeApp","contents":[{"annotation":[{"start":[94,52],"name":"bower_components/purescript-node-http/src/Node/HTTP.purs","end":[94,57]},[]],"tag":"TypeConstructor","contents":[["Prim"],"Array"]},{"annotation":[{"start":[94,58],"name":"bower_components/purescript-node-http/src/Node/HTTP.purs","end":[94,64]},[]],"tag":"TypeConstructor","contents":[["Prim"],"String"]}]}]},{"annotation":[{"start":[94,68],"name":"bower_components/purescript-node-http/src/Node/HTTP.purs","end":[94,79]},[]],"tag":"TypeApp","contents":[{"annotation":[{"start":[94,68],"name":"bower_components/purescript-node-http/src/Node/HTTP.purs","end":[94,74]},[]],"tag":"TypeConstructor","contents":[["Effect"],"Effect"]},{"annotation":[{"start":[94,75],"name":"bower_components/purescript-node-http/src/Node/HTTP.purs","end":[94,79]},[]],"tag":"TypeConstructor","contents":[["Data","Unit"],"Unit"]}]}]}]}]}}},{"EDValue":{"edValueName":{"Ident":"setStatusCode"},"edValueType":{"annotation":[{"start":[97,33],"name":"bower_components/purescript-node-http/src/Node/HTTP.purs","end":[97,63]},[]],"tag":"TypeApp","contents":[{"annotation":[{"start":[97,33],"name":"bower_components/purescript-node-http/src/Node/HTTP.purs","end":[97,63]},[]],"tag":"TypeApp","contents":[{"annotation":[{"start":[97,42],"name":"bower_components/purescript-node-http/src/Node/HTTP.purs","end":[97,44]},[]],"tag":"TypeConstructor","contents":[["Prim"],"Function"]},{"annotation":[{"start":[97,33],"name":"bower_components/purescript-node-http/src/Node/HTTP.purs","end":[97,41]},[]],"tag":"TypeConstructor","contents":[["Node","HTTP"],"Response"]}]},{"annotation":[{"start":[97,45],"name":"bower_components/purescript-node-http/src/Node/HTTP.purs","end":[97,63]},[]],"tag":"TypeApp","contents":[{"annotation":[{"start":[97,45],"name":"bower_components/purescript-node-http/src/Node/HTTP.purs","end":[97,63]},[]],"tag":"TypeApp","contents":[{"annotation":[{"start":[97,49],"name":"bower_components/purescript-node-http/src/Node/HTTP.purs","end":[97,51]},[]],"tag":"TypeConstructor","contents":[["Prim"],"Function"]},{"annotation":[{"start":[97,45],"name":"bower_components/purescript-node-http/src/Node/HTTP.purs","end":[97,48]},[]],"tag":"TypeConstructor","contents":[["Prim"],"Int"]}]},{"annotation":[{"start":[97,52],"name":"bower_components/purescript-node-http/src/Node/HTTP.purs","end":[97,63]},[]],"tag":"TypeApp","contents":[{"annotation":[{"start":[97,52],"name":"bower_components/purescript-node-http/src/Node/HTTP.purs","end":[97,58]},[]],"tag":"TypeConstructor","contents":[["Effect"],"Effect"]},{"annotation":[{"start":[97,59],"name":"bower_components/purescript-node-http/src/Node/HTTP.purs","end":[97,63]},[]],"tag":"TypeConstructor","contents":[["Data","Unit"],"Unit"]}]}]}]}}},{"EDValue":{"edValueName":{"Ident":"setStatusMessage"},"edValueType":{"annotation":[{"start":[100,36],"name":"bower_components/purescript-node-http/src/Node/HTTP.purs","end":[100,69]},[]],"tag":"TypeApp","contents":[{"annotation":[{"start":[100,36],"name":"bower_components/purescript-node-http/src/Node/HTTP.purs","end":[100,69]},[]],"tag":"TypeApp","contents":[{"annotation":[{"start":[100,45],"name":"bower_components/purescript-node-http/src/Node/HTTP.purs","end":[100,47]},[]],"tag":"TypeConstructor","contents":[["Prim"],"Function"]},{"annotation":[{"start":[100,36],"name":"bower_components/purescript-node-http/src/Node/HTTP.purs","end":[100,44]},[]],"tag":"TypeConstructor","contents":[["Node","HTTP"],"Response"]}]},{"annotation":[{"start":[100,48],"name":"bower_components/purescript-node-http/src/Node/HTTP.purs","end":[100,69]},[]],"tag":"TypeApp","contents":[{"annotation":[{"start":[100,48],"name":"bower_components/purescript-node-http/src/Node/HTTP.purs","end":[100,69]},[]],"tag":"TypeApp","contents":[{"annotation":[{"start":[100,55],"name":"bower_components/purescript-node-http/src/Node/HTTP.purs","end":[100,57]},[]],"tag":"TypeConstructor","contents":[["Prim"],"Function"]},{"annotation":[{"start":[100,48],"name":"bower_components/purescript-node-http/src/Node/HTTP.purs","end":[100,54]},[]],"tag":"TypeConstructor","contents":[["Prim"],"String"]}]},{"annotation":[{"start":[100,58],"name":"bower_components/purescript-node-http/src/Node/HTTP.purs","end":[100,69]},[]],"tag":"TypeApp","contents":[{"annotation":[{"start":[100,58],"name":"bower_components/purescript-node-http/src/Node/HTTP.purs","end":[100,64]},[]],"tag":"TypeConstructor","contents":[["Effect"],"Effect"]},{"annotation":[{"start":[100,65],"name":"bower_components/purescript-node-http/src/Node/HTTP.purs","end":[100,69]},[]],"tag":"TypeConstructor","contents":[["Data","Unit"],"Unit"]}]}]}]}}},{"EDValue":{"edValueName":{"Ident":"responseAsStream"},"edValueType":{"annotation":[{"start":[103,21],"name":"bower_components/purescript-node-http/src/Node/HTTP.purs","end":[103,44]},[]],"tag":"TypeApp","contents":[{"annotation":[{"start":[103,21],"name":"bower_components/purescript-node-http/src/Node/HTTP.purs","end":[103,44]},[]],"tag":"TypeApp","contents":[{"annotation":[{"start":[103,30],"name":"bower_components/purescript-node-http/src/Node/HTTP.purs","end":[103,32]},[]],"tag":"TypeConstructor","contents":[["Prim"],"Function"]},{"annotation":[{"start":[103,21],"name":"bower_components/purescript-node-http/src/Node/HTTP.purs","end":[103,29]},[]],"tag":"TypeConstructor","contents":[["Node","HTTP"],"Response"]}]},{"annotation":[{"start":[65,19],"name":"bower_components/purescript-node-streams/src/Node/Stream.purs","end":[65,41]},[]],"tag":"TypeApp","contents":[{"annotation":[{"start":[65,19],"name":"bower_components/purescript-node-streams/src/Node/Stream.purs","end":[65,25]},[]],"tag":"TypeConstructor","contents":[["Node","Stream"],"Stream"]},{"annotation":[{"start":[65,27],"name":"bower_components/purescript-node-streams/src/Node/Stream.purs","end":[65,41]},[]],"tag":"RCons","contents":["write",{"annotation":[{"start":[65,36],"name":"bower_components/purescript-node-streams/src/Node/Stream.purs","end":[65,41]},[]],"tag":"TypeConstructor","contents":[["Node","Stream"],"Write"]},{"annotation":[{"start":[103,43],"name":"bower_components/purescript-node-http/src/Node/HTTP.purs","end":[103,44]},[]],"tag":"REmpty"}]}]}]}}}],"efSourceSpan":{"start":[3,1],"name":"bower_components/purescript-node-http/src/Node/HTTP.purs","end":[104,32]}}